[
  {
    "filename": "ロジーナピンクピコティ.jpeg",
    "x": 0.09369000792503357,
    "y": -5.607514381408691
  },
  {
    "filename": "チェリーテッシノ.jpeg",
    "x": 1.0562291145324707,
    "y": -4.973927974700928
  },
  {
    "filename": "グズマニア『サブリナ』.jpeg",
    "x": -0.44745126366615295,
    "y": -4.757957458496094
  },
  {
    "filename": "ピンクラナンキュラ.jpeg",
    "x": 0.5094228386878967,
    "y": -1.092179775238037
  },
  {
    "filename": "マルガリータ.jpeg",
    "x": 1.1737172603607178,
    "y": -4.358821868896484
  },
  {
    "filename": "マリーサイモン.jpeg",
    "x": -0.5902372002601624,
    "y": -2.2590749263763428
  },
  {
    "filename": "スカイライン.jpeg",
    "x": 0.29738670587539673,
    "y": 0.032005634158849716
  },
  {
    "filename": "ブレンダ.jpeg",
    "x": 1.326276183128357,
    "y": -4.1576948165893555
  },
  {
    "filename": "マリポサ.jpeg",
    "x": -0.37561318278312683,
    "y": -1.7556002140045166
  },
  {
    "filename": "ピンクキャンディケーン.jpeg",
    "x": 0.45121097564697266,
    "y": -3.4093804359436035
  },
  {
    "filename": "ソルボンヌ.jpeg",
    "x": 1.3300167322158813,
    "y": -0.2439025640487671
  },
  {
    "filename": "アリシア.jpeg",
    "x": 0.8774632811546326,
    "y": -2.0924813747406006
  },
  {
    "filename": "スーパーセンセーション.jpeg",
    "x": 0.418290913105011,
    "y": -4.617650508880615
  },
  {
    "filename": "恋心.jpeg",
    "x": 0.4801512062549591,
    "y": -2.510944128036499
  },
  {
    "filename": "バイパー.jpeg",
    "x": 1.3085172176361084,
    "y": -4.615646839141846
  },
  {
    "filename": "ピンクワルツ.jpeg",
    "x": 1.722022533416748,
    "y": -0.05857741832733154
  },
  {
    "filename": "エースピンク.jpeg",
    "x": 1.2480673789978027,
    "y": -3.3049566745758057
  },
  {
    "filename": "ボヤージュライトアプリコット.jpeg",
    "x": -0.7942608594894409,
    "y": -3.6681182384490967
  },
  {
    "filename": "マキシマ.jpeg",
    "x": -0.3846157193183899,
    "y": -5.370069980621338
  },
  {
    "filename": "ドンセル.jpeg",
    "x": 0.23471957445144653,
    "y": -2.9085419178009033
  },
  {
    "filename": "バイパーワイン.jpeg",
    "x": 0.8104552626609802,
    "y": -6.637382507324219
  },
  {
    "filename": "ロイヤルテン.jpeg",
    "x": 1.188352346420288,
    "y": -5.28188419342041
  },
  {
    "filename": "ロサーノシャルロッテダーク.jpeg",
    "x": 0.8129853010177612,
    "y": -2.278470516204834
  },
  {
    "filename": "セレブクイーン.jpeg",
    "x": 0.25184834003448486,
    "y": -1.6966495513916016
  },
  {
    "filename": "セレブピンク.jpeg",
    "x": 0.8323184251785278,
    "y": -6.71694278717041
  },
  {
    "filename": "ミヌエット.jpeg",
    "x": 1.1600356101989746,
    "y": -0.8254659175872803
  },
  {
    "filename": "パーティラナンキュラ.jpeg",
    "x": 0.7465774416923523,
    "y": 0.022853992879390717
  },
  {
    "filename": "キノシフォン.jpeg",
    "x": 0.6411706209182739,
    "y": -0.1826769858598709
  },
  {
    "filename": "ジュミリア.jpeg",
    "x": 0.8897389769554138,
    "y": -6.1246337890625
  },
  {
    "filename": "アミコ.jpeg",
    "x": 1.490028738975525,
    "y": 1.1453790664672852
  },
  {
    "filename": "エンジェルヴェール.jpeg",
    "x": 0.7263424396514893,
    "y": -0.9611837267875671
  },
  {
    "filename": "ンクレディブル！.jpeg",
    "x": -0.40897369384765625,
    "y": -2.466702699661255
  },
  {
    "filename": "ブロッサムピンク.jpeg",
    "x": 1.767574667930603,
    "y": -0.3105153739452362
  },
  {
    "filename": "キャンディータフト.jpeg",
    "x": 1.368848443031311,
    "y": -3.390868902206421
  },
  {
    "filename": "ソネットフレーズ.jpeg",
    "x": 0.8561941385269165,
    "y": 0.5737645030021667
  },
  {
    "filename": "スプラッシュセンセーション.jpeg",
    "x": 1.154349446296692,
    "y": -3.2101948261260986
  },
  {
    "filename": "ソネットハーティ.jpeg",
    "x": 1.1569539308547974,
    "y": -0.8499861359596252
  },
  {
    "filename": "ボヌール.jpeg",
    "x": 0.5355276465415955,
    "y": -5.846425533294678
  },
  {
    "filename": "シャンディピンク.jpeg",
    "x": 1.0588089227676392,
    "y": -3.9426958560943604
  },
  {
    "filename": "ロジーナブルーピコティ.jpeg",
    "x": 0.7692247629165649,
    "y": -3.8432726860046387
  },
  {
    "filename": "ファンシーローラ.jpeg",
    "x": 1.6592776775360107,
    "y": -0.15257060527801514
  },
  {
    "filename": "フィスタ.jpeg",
    "x": 0.3457033038139343,
    "y": -1.654551386833191
  },
  {
    "filename": "ファルファリーナ.jpeg",
    "x": 0.8711153268814087,
    "y": 0.13594235479831696
  },
  {
    "filename": "シャララピコ.jpeg",
    "x": 0.36350417137145996,
    "y": -6.295027732849121
  },
  {
    "filename": "アーリエス.jpeg",
    "x": 1.1232340335845947,
    "y": -1.9380642175674438
  },
  {
    "filename": "スイートダイヤモンド.jpeg",
    "x": 0.8038835525512695,
    "y": -4.81513786315918
  },
  {
    "filename": "プリマドンナ.jpeg",
    "x": -0.0067067756317555904,
    "y": -4.121011734008789
  },
  {
    "filename": "ノーブルライト.jpeg",
    "x": 1.2887353897094727,
    "y": -2.9946846961975098
  },
  {
    "filename": "チェリオ.jpeg",
    "x": -0.4988221526145935,
    "y": -4.537454605102539
  },
  {
    "filename": "グラナスライト.jpeg",
    "x": -0.7959075570106506,
    "y": -2.6904337406158447
  },
  {
    "filename": "クラリスピンク.jpeg",
    "x": 0.5423998236656189,
    "y": -5.995218753814697
  },
  {
    "filename": "スパークリンググラフィティ.jpeg",
    "x": 1.4662362337112427,
    "y": -0.18241383135318756
  },
  {
    "filename": "ピンクパフェ.jpeg",
    "x": 1.1429535150527954,
    "y": -0.6117223501205444
  },
  {
    "filename": "ムーンワルツ.jpeg",
    "x": 1.126458764076233,
    "y": -4.923806667327881
  },
  {
    "filename": "アライアンス.jpeg",
    "x": 2.032518148422241,
    "y": -1.8965647220611572
  },
  {
    "filename": "ローズゼラニウム.jpeg",
    "x": 1.0666066408157349,
    "y": -0.32794883847236633
  }
]
